server/__init__.py
server/server.py
server/common/__init__.py
server/common/decors.py
server/common/descripts.py
server/common/errors.py
server/common/metaclasses.py
server/common/utils.py
server/common/variables.py
server/log/__init__.py
server/log/client_log_config.py
server/log/server_log_config.py
server/server/__init__.py
server/server/add_user.py
server/server/config_window.py
server/server/core.py
server/server/database.py
server/server/main_window.py
server/server/remove_user.py
server/server/stat_window.py
server/tests/__init__.py
server/tests/test_client.py
server/tests/test_server.py
server/tests/test_utils.py
py_messenger_server_VM-0.2.0.dist-info/METADATA
py_messenger_server_VM-0.2.0.dist-info/WHEEL
py_messenger_server_VM-0.2.0.dist-info/top_level.txt
py_messenger_server_VM-0.2.0.dist-info/RECORD
