Metadata-Version: 2.1
Name: py-messenger-server-VM
Version: 0.2.0
Summary: Mess Server
Home-page: UNKNOWN
Author: Vikulov M
Author-email: vikulov.1991@mail.ru
License: UNKNOWN
Platform: UNKNOWN
Requires-Dist: PyQt5
Requires-Dist: sqlalchemy
Requires-Dist: pycryptodome
Requires-Dist: pycryptodomex
